pystreamfs/__init__.py
pystreamfs/plots.py
pystreamfs/pystreamfs.py
pystreamfs/utils.py
pystreamfs/algorithms/__init__.py
pystreamfs/algorithms/cancelout.py
pystreamfs/algorithms/efs.py
pystreamfs/algorithms/fsds.py
pystreamfs/algorithms/mcnn.py
pystreamfs/algorithms/ofs.py
pystreamfs-0.0.6.dist-info/LICENSE
pystreamfs-0.0.6.dist-info/METADATA
pystreamfs-0.0.6.dist-info/WHEEL
pystreamfs-0.0.6.dist-info/top_level.txt
pystreamfs-0.0.6.dist-info/RECORD
