Metadata-Version: 2.1
Name: pystreamfs
Version: 0.0.6
Summary: A Python package for feature selection on a simulated data stream
Home-page: https://github.com/haugjo/pystreamfs
Author: Johannes Haug
Author-email: johannes-christian.haug@uni-tuebingen.de
License: UNKNOWN
Platform: UNKNOWN
Classifier: Programming Language :: Python :: 3
Classifier: License :: OSI Approved :: MIT License
Classifier: Operating System :: OS Independent
